{
	"alltp": [
		"library.js",
		"comment.otp.html",
		"template.json",
		"archives.otp.html",
		"cloth.otp.html",
		"main.otp.html",
		"main.js",
		"post.otp.html",
		"postitem.otp.html",
		"postlist.otp.html",
		"style.css",
		"tags.otp.html",
		"main.json",
		"loading.otp.html",
		"search.js"
	],
	"necessary": [
		"cloth.otp.html",
		"main.otp.html",
		"comment.otp.html"
	],
	"include": [
		"index.otp.html",
		"tag.otp.html",
		"archive.otp.html",
		"comment.otp.html",
		"template.json",
		"archives.otp.html",
		"cloth.otp.html",
		"main.otp.html",
		"main.js",
		"search.js",
		"main.json",
		"post.otp.html",
		"postitem.otp.html",
		"postlist.otp.html",
		"style.css",
		"tags.otp.html",
		"loading.otp.html"
	],
	"usemain": [
		"postlist.otp.html",
		"archives.otp.html",
		"tags.otp.html"
	],
	"templatehtmls": {
		"postitem": "postitem.otp.html",
		"postlist": "postlist.otp.html",
		"post": "post.otp.html",
		"tags": "tags.otp.html",
		"main": "main.otp.html",
		"comment": "comment.otp.html",
		"cloth": "cloth.otp.html",
		"archives": "archives.otp.html"
	},
	"generatehtmls": {
		"tags": "tags.html",
		"archives": "archives.html"
	},
	"mainjson": "main.json"
}